{"WEAPONS":{"name":"Weapons","key":"weapons","unit":"\u003c\u003e"},"POWER_PLANTS":{"name":"Power Plants","key":"power_plants","unit":"\u003c\u003e"},"SHIELD_GENERATORS":{"name":"Shield Generators","key":"shield_generators","unit":"\u003c\u003e"},"UTILITY_ITEMS":{"name":"Utility Items","key":"utility_items","unit":"\u003c\u003e"},"MISSILES":{"name":"Missiles","key":"missiles","unit":"\u003c\u003e"},"TURRETS":{"name":"Turrets","key":"turrets","unit":"\u003c\u003e"},"MAIN_THRUSTERS":{"name":"Main Thrusters","key":"main_thrusters","unit":"\u003c\u003e"},"MANEUVERING_THRUSTERS":{"name":"Maneuvering Thrusters","key":"maneuvering_thrusters","unit":"\u003c\u003e"},"RADAR":{"name":"Radar","key":"radar","unit":"\u003c\u003e"},"COMPUTERS":{"name":"Computers","key":"computers","unit":"\u003c\u003e"},"FUEL_INTAKES":{"name":"Fuel Intakes","key":"fuel_intakes","unit":"\u003c\u003e"},"FUEL_TANKS":{"name":"Fuel Tanks","key":"fuel_tanks","unit":"\u003c\u003e"},"QUANTUM_DRIVES":{"name":"Quantum Drives","key":"quantum_drives","unit":"\u003c\u003e"},"JUMP_MODULES":{"name":"Jump Modules","key":"jump_modules","unit":"\u003c\u003e"},"QUANTUM_FUEL_TANKS":{"name":"Quantum Fuel Tanks","key":"quantum_fuel_tanks","unit":"\u003c\u003e"},"COOLERS":{"name":"Coolers","key":"coolers","unit":"\u003c\u003e"},"COUNTERMEASURES":{"name":"Countermeasures","key":"countermeasures","unit":"\u003c\u003e"}}